loggingbootstrap/__init__.py
loggingbootstrap/settings.py
pge_plugin_terminal/__init__.py
pge_plugin_terminal/settings.py
pge_plugin_terminal/terminal_window.py
pge_plugin_terminal/models/__init__.py
pge_plugin_terminal/models/projects/__init__.py
pge_plugin_terminal/models/projects/projects_terminal.py
pybpod_alyx_module/__init__.py
pybpod_alyx_module/alyx_details.py
pybpod_alyx_module/module.py
pybpod_alyx_module/module_api.py
pybpod_alyx_module/module_gui.py
pybpod_alyx_module/settings.py
pybpod_alyx_module/alyxapi/__init__.py
pybpod_alyx_module/alyxapi/alyxapi.py
pybpod_alyx_module/alyxapi/alyxconf.py
pybpod_alyx_module/alyxapi/data/__init__.py
pybpod_alyx_module/alyxapi/data/data.py
pybpod_alyx_module/alyxapi/data/get.py
pybpod_alyx_module/alyxapi/data/post.py
pybpod_alyx_module/alyxapi/subjects/__init__.py
pybpod_alyx_module/alyxapi/subjects/get.py
pybpod_alyx_module/alyxapi/subjects/post.py
pybpod_alyx_module/alyxapi/subjects/subjects.py
pybpod_alyx_module/models/__init__.py
pybpod_alyx_module/models/project/__init__.py
pybpod_alyx_module/models/project/project_treenode.py
pybpod_alyx_module/models/subject/__init__.py
pybpod_alyx_module/models/subject/alyx_subject.py
pybpod_alyx_module/models/user/__init__.py
pybpod_alyx_module/models/user/user_window.py
pybpod_gui_plugin_emulator/__init__.py
pybpod_gui_plugin_emulator/emulator_gui.py
pybpod_gui_plugin_emulator/settings.py
pybpod_gui_plugin_emulator/models/__init__.py
pybpod_gui_plugin_emulator/models/setup/__init__.py
pybpod_gui_plugin_emulator/models/setup/setup_uibusy_emulator.py
pybpod_gui_plugin_emulator/models/setup/setup_window_emulator.py
pybpod_gui_plugin_emulator/resources/__init__.py
pybpod_rotaryencoder_module/__init__.py
pybpod_rotaryencoder_module/module.py
pybpod_rotaryencoder_module/module_api.py
pybpod_rotaryencoder_module/module_gui.py
pybpod_rotaryencoder_module/settings.py
pybpod_rotaryencoder_module/models/__init__.py
pybpod_rotaryencoder_module/models/projects/__init__.py
iblpybpod-2.0.3.dist-info/LICENSE
iblpybpod-2.0.3.dist-info/METADATA
iblpybpod-2.0.3.dist-info/WHEEL
iblpybpod-2.0.3.dist-info/entry_points.txt
iblpybpod-2.0.3.dist-info/top_level.txt
iblpybpod-2.0.3.dist-info/RECORD
