Metadata-Version: 2.1
Name: iblpybpod
Version: 2.0.3
Summary: IBL implementation of pybpod software
Home-page: https://github.com/int-brain-lab/iblpybpod/
Author: IBL Staff
License: MIT
Requires-Python: >3.8.0
License-File: LICENSE
Requires-Dist: aenum
Requires-Dist: AnyQt
Requires-Dist: confapp
Requires-Dist: markdown2
Requires-Dist: matplotlib
Requires-Dist: numpy
Requires-Dist: pandas
Requires-Dist: PyOpenGL
Requires-Dist: PyQt5
Requires-Dist: PyQtWebEngine
Requires-Dist: pyserial
Requires-Dist: pyusb
Requires-Dist: PyYAML
Requires-Dist: QScintilla
Requires-Dist: scipy
Requires-Dist: visvis
Requires-Dist: opencv-python (==4.3.0.36) ; sys_platform != "win32"
Requires-Dist: opencv-python ; sys_platform == "win32"
